pamfax/__init__.py
pamfax/processors/__init__.py
a1pamfax-0.0.9.dist-info/LICENSE.txt
a1pamfax-0.0.9.dist-info/METADATA
a1pamfax-0.0.9.dist-info/WHEEL
a1pamfax-0.0.9.dist-info/top_level.txt
a1pamfax-0.0.9.dist-info/RECORD
