Metadata-Version: 2.1
Name: a1pamfax
Version: 0.0.9
Summary: Python 3 implementation for the PamFax API
Home-page: http://github.com/bufemc/a1pamfax/
Author: Marc Bufe (Airport1)
Author-email: bufemc@gmail.com
License: LICENSE.txt
Platform: UNKNOWN
Classifier: Development Status :: 4 - Beta
Classifier: Programming Language :: Python
Classifier: Programming Language :: Python :: 3.6
Classifier: License :: OSI Approved :: MIT License
Classifier: Operating System :: OS Independent
Requires-Python: >=3.6
